{
    "version": "0.19.0",
    "description": "A TUI for analyzing .NET assemblies",
    "homepage": "https://github.com/willibrandon/dotsider",
    "license": "MIT",
    "architecture": {
        "64bit": {
            "url": "https://github.com/willibrandon/dotsider/releases/download/v0.19.0/dotsider-win-x64.zip",
            "hash": "6b3dc914968ffa01b3c0d01877b59553f2308ecd4970a50165bc14164b17d6dd"
        },
        "arm64": {
            "url": "https://github.com/willibrandon/dotsider/releases/download/v0.19.0/dotsider-win-arm64.zip",
            "hash": "3c518a29a0e574ae78c137bba46fa49fc4236305025ea831adbbb560087216f3"
        }
    },
    "bin": "dotsider.exe",
    "checkver": "github",
    "autoupdate": {
        "architecture": {
            "64bit": {
                "url": "https://github.com/willibrandon/dotsider/releases/download/v$version/dotsider-win-x64.zip"
            },
            "arm64": {
                "url": "https://github.com/willibrandon/dotsider/releases/download/v$version/dotsider-win-arm64.zip"
            }
        },
        "hash": {
            "url": "$url.sha256"
        }
    }
}
